text_lens/__init__.py
text_lens/__main__.py
text_lens/app.py
text_lens/hotkey_daemon.py
text_lens/text-lens-logo.png
text_lens-1.0.1.dist-info/METADATA
text_lens-1.0.1.dist-info/WHEEL
text_lens-1.0.1.dist-info/entry_points.txt
text_lens-1.0.1.dist-info/licenses/LICENSE
text_lens-1.0.1.dist-info/RECORD
