Metadata-Version: 2.4
Name: text-lens
Version: 1.0.1
Summary: A text analysis tool
Author-email: Adrian Rubio Punal <adrian.rubio.punal@gmail.com>
License: MIT
License-File: LICENSE
Requires-Python: >=3.8
Requires-Dist: matplotlib
Requires-Dist: pillow
Requires-Dist: textstat
Requires-Dist: tiktoken
Requires-Dist: vadersentiment
